{"quiz_meta": {"title": "Skrining Psikologis - Calon Perawat", "description": "Tes screening awal untuk evaluasi kepribadian, stress resilience, dan emotional intelligence calon perawat", "target_position": "Perawat", "duration_minutes": 30, "created_date": "2026-07-22", "language": "id", "total_questions": 75}, "ideal_scores": {"Agreeableness": {"min": 4.2, "ideal": 4.6, "importance": "CRITICAL - Patient empathy"},  "Conscientiousness": {"min": 4.0, "ideal": 4.5, "importance": "HIGH - Attention to detail"}, "Emotional_Stability": {"min": 3.5, "ideal": 4.0, "importance": "HIGH - Burnout prevention"}, "EQ_Overall": {"min": 3.8, "ideal": 4.3, "importance": "HIGH - Patient communication"}, "Stress_Resilience": {"min": 3.5, "ideal": 4.2, "importance": "CRITICAL - Emergency situations"}}, "key_differences_from_doctor": {"primary_focus": "Patient care dan empati lebih penting daripada decision-making", "stress_factors": "Shift work, physical demands, emotional demands pasien", "team_dynamics": "Kolaborasi dengan dokter dan staff lain sangat penting", "competencies": ["Patient advocacy", "Emotional resilience", "Teamwork", "Physical stamina", "Crisis management"]}, "red_flags": {"agreeableness_low": {"threshold": 3.5, "severity": "CRITICAL", "note": "Kurang empati - fundamental untuk perawatan pasien"}, "neuroticism_high": {"threshold": 4.0, "severity": "HIGH", "note": "Risiko burnout tinggi - perawat sering menghadapi emotional stress"}, "stress_resilience_low": {"threshold": 3.5, "severity": "CRITICAL", "note": "Tidak siap untuk emergency dan situasi high-pressure"}, "conscientiousness_low": {"threshold": 3.5, "severity": "MEDIUM", "note": "Detail penting dalam patient care dan medication"}}}